{
  "users": [{
      "id": 1,
      "username": "teonv",
      "password": "iloveyou",
      "fullname": "Nguyễn Văn Tèo",
      "email": "teonv@fpt.edu.vn",
      "gender": "true",
      "birthday": "1995-12-21",
      "schoolfee": "1500000",
      "marks": "0"
    },
    {
      "id": 2,
      "username": "pheonv",
      "password": "iloveyou",
      "fullname": "Nguyễn Văn Chí Phèo",
      "email": "pheonv@fpt.edu.vn",
      "gender": "true",
      "birthday": "1985-10-11",
      "schoolfee": "2500000",
      "marks": "0"
    },
    {
      "id": 3,
      "username": "nopt",
      "password": "iloveyou",
      "fullname": "Phạm Thị Nở",
      "email": "nopt@fpt.edu.vn",
      "gender": "false",
      "birthday": "1993-05-15",
      "schoolfee": "2000000",
      "marks": "0"
    },
    {
      "username": "admin",
      "password": "123",
      "fullname": "Nguyễn Danh Tiến",
      "email": "tienndpd03947@fpt.edu.vn",
      "gender": "true",
      "birthday": "1995-12-21",
      "schoolfee": "1500000",
      "marks": "0",
      "id": 4
    }
  ],
  "histories": [{
      "user_id": 4,
      "subject": "SQL Server",
      "marks": "9.00",
      "id": 1
    },
    {
      "user_id": 4,
      "subject": "Lập trình ASP.NET",
      "marks": "10.00",
      "id": 2
    },
    {
      "user_id": 1,
      "subject": "Điện toán đám mây",
      "marks": "10.00",
      "id": 3
    },
    {
      "user_id": 1,
      "subject": "HTML5 và CSS3",
      "marks": "10.00",
      "id": 4
    },
    {
      "user_id": 4,
      "subject": "Lập trình PHP",
      "marks": "10.00",
      "id": 5
    },
    {
      "user_id": 2,
      "subject": "Quản lý dự án với Agile",
      "marks": "10.00",
      "id": 6
    },
    {
      "user_id": 2,
      "subject": "Điện toán đám mây",
      "marks": "6.00",
      "id": 7
    },
    {
      "user_id": 3,
      "subject": "Lập trình hướng đối tượng với Java",
      "marks": "10.00",
      "id": 8
    },
    {
      "user_id": 3,
      "subject": "HTML5 và CSS3",
      "marks": "10.00",
      "id": 9
    },
    {
      "user_id": 3,
      "subject": "Thiết kế layout",
      "marks": "10.00",
      "id": 10
    },
    {
      "user_id": 3,
      "subject": "Lập trình game 2D",
      "marks": "10.00",
      "id": 11
    },
    {
      "user_id": 3,
      "subject": "Lập trình game 2D",
      "marks": "0.00",
      "id": 12
    }

  ]
}